audiomap/__init__.py
audiomap/cli.py
audiomap/detector.py
audiomap/exceptions.py
audiomap/utils.py
audiomap-1.0.2.dist-info/WHEEL
audiomap-1.0.2.dist-info/entry_points.txt
audiomap-1.0.2.dist-info/METADATA
audiomap-1.0.2.dist-info/RECORD
