Metadata-Version: 2.4
Name: audiomap
Version: 1.0.2
Summary: Cross-platform audio device mapping with UID support
Keywords: audio,device,detection,uid,cross-platform,macos,windows,linux,coreaudio,wasapi,alsa
Author: Andy Lee
Author-email: Andy Lee <mail@andylee.tw>
License-Expression: MIT
Classifier: Development Status :: 4 - Beta
Classifier: Intended Audience :: Developers
Classifier: Operating System :: OS Independent
Classifier: Programming Language :: Python :: 3
Classifier: Programming Language :: Python :: 3.12
Classifier: Programming Language :: Python :: 3.13
Classifier: Topic :: Multimedia :: Sound/Audio
Classifier: Topic :: Software Development :: Libraries :: Python Modules
Requires-Dist: pytest>=7.0.0 ; extra == 'dev'
Requires-Dist: pytest-cov>=4.0.0 ; extra == 'dev'
Requires-Dist: comtypes>=1.4.11 ; extra == 'windows'
Requires-Dist: pycaw>=20240210 ; extra == 'windows'
Requires-Python: >=3.12
Project-URL: Homepage, https://github.com/andylee830914/audiomap
Project-URL: Issues, https://github.com/andylee830914/audiomap/issues
Project-URL: Repository, https://github.com/andylee830914/audiomap.git
Provides-Extra: dev
Provides-Extra: windows
